pretix_cashfree/__init__.py
pretix_cashfree/apps.py
pretix_cashfree/constants.py
pretix_cashfree/models.py
pretix_cashfree/payment.py
pretix_cashfree/signals.py
pretix_cashfree/urls.py
pretix_cashfree/utils.py
pretix_cashfree/views.py
pretix_cashfree/locale/de/LC_MESSAGES/django.mo
pretix_cashfree/locale/de/LC_MESSAGES/django.po
pretix_cashfree/locale/de_Informal/.gitkeep
pretix_cashfree/locale/de_Informal/LC_MESSAGES/django.mo
pretix_cashfree/locale/de_Informal/LC_MESSAGES/django.po
pretix_cashfree/migrations/0001_initial.py
pretix_cashfree/migrations/0002_delete_paymentwebhookevent.py
pretix_cashfree/migrations/0003_rename_order_id_paymentattempt_reference.py
pretix_cashfree/migrations/__init__.py
pretix_cashfree/static/pretix_cashfree/.gitkeep
pretix_cashfree/static/pretix_cashfree/images/CF_Logo_dark-WhiteBG.svg
pretix_cashfree/templates/pretix_cashfree/.gitkeep
pretix_cashfree/templates/pretix_cashfree/checkout_confirm.html
pretix_cashfree/templates/pretix_cashfree/payment_control.html
pretix_cashfree/templates/pretix_cashfree/redirect.html
pretix_cashfree/templates/pretix_cashfree/refund_control.html
pretix_cashfree-1.0.6.dist-info/licenses/LICENSE
pretix_cashfree-1.0.6.dist-info/METADATA
pretix_cashfree-1.0.6.dist-info/WHEEL
pretix_cashfree-1.0.6.dist-info/entry_points.txt
pretix_cashfree-1.0.6.dist-info/top_level.txt
pretix_cashfree-1.0.6.dist-info/RECORD
