Metadata-Version: 2.4
Name: pretix-cashfree
Version: 1.0.6
Summary: Pretix plugin for accepting payments via Cashfree.
Author: Diptangshu Chakrabarty
Author-email: Diptangshu Chakrabarty <cdiptangshu@gmail.com>
Maintainer-email: Diptangshu Chakrabarty <cdiptangshu@gmail.com>
License: Apache
Project-URL: homepage, https://github.com/cdiptangshu/pretix-cashfree
Project-URL: repository, https://github.com/cdiptangshu/pretix-cashfree
Keywords: pretix
License-File: LICENSE
Requires-Dist: cashfree_pg
Dynamic: author
Dynamic: license-file
